asoct_mcd/classification/__init__.py
asoct_mcd/classification/factories.py
asoct_mcd/classification/interfaces.py
asoct_mcd/classification/implementations/__init__.py
asoct_mcd/classification/implementations/cell_classifier.py
asoct_mcd/image_processing/__init__.py
asoct_mcd/image_processing/image_operations.py
asoct_mcd/image_processing/mask_operations.py
asoct_mcd/model_implementations/__init__.py
asoct_mcd/model_implementations/sam_vit_b/__init__.py
asoct_mcd/model_implementations/sam_vit_b/config.py
asoct_mcd/model_implementations/sam_vit_b/wrapper.py
asoct_mcd/model_implementations/spatial_attention/__init__.py
asoct_mcd/model_implementations/spatial_attention/config.py
asoct_mcd/model_implementations/spatial_attention/wrapper.py
asoct_mcd/model_management/__init__.py
asoct_mcd/model_management/config.py
asoct_mcd/model_management/factory.py
asoct_mcd/model_management/interfaces.py
asoct_mcd/model_management/loaders.py
asoct_mcd/pipeline/__init__.py
asoct_mcd/pipeline/builder.py
asoct_mcd/pipeline/config.py
asoct_mcd/pipeline/pipeline.py
asoct_mcd/pipeline/result.py
asoct_mcd/pipeline/wrappers.py
asoct_mcd/preprocessing/__init__.py
asoct_mcd/preprocessing/factories.py
asoct_mcd/preprocessing/interfaces.py
asoct_mcd/preprocessing/pipeline.py
asoct_mcd/preprocessing/implementations/__init__.py
asoct_mcd/preprocessing/implementations/converters.py
asoct_mcd/preprocessing/implementations/denoisers.py
asoct_mcd/prompt_generation/__init__.py
asoct_mcd/prompt_generation/factories.py
asoct_mcd/prompt_generation/interfaces.py
asoct_mcd/prompt_generation/implementations/__init__.py
asoct_mcd/prompt_generation/implementations/i2acp.py
asoct_mcd/segmentation/__init__.py
asoct_mcd/segmentation/factories.py
asoct_mcd/segmentation/interfaces.py
asoct_mcd/segmentation/implementations/__init__.py
asoct_mcd/segmentation/implementations/trained.py
asoct_mcd/segmentation/implementations/zero_shot.py
asoct_mcd/threshold_methods/__init__.py
asoct_mcd/threshold_methods/factories.py
asoct_mcd-0.2.1.dist-info/METADATA
asoct_mcd-0.2.1.dist-info/WHEEL
asoct_mcd-0.2.1.dist-info/top_level.txt
asoct_mcd-0.2.1.dist-info/RECORD
