Metadata-Version: 2.4
Name: asoct-mcd
Version: 0.2.1
Summary: Minuscule Cell Detection in AS-OCT Medical Images
Author: B. Chen
Maintainer: B. Chen
License: MIT
Project-URL: github, https://github.com/joeybyc/MCD
Keywords: medical-imaging,cell-detection,optical-coherence-tomography,computer-vision,deep-learning
Classifier: Intended Audience :: Science/Research
Classifier: Intended Audience :: Healthcare Industry
Classifier: Operating System :: OS Independent
Classifier: Programming Language :: Python :: 3
Classifier: Programming Language :: Python :: 3.9
Classifier: Programming Language :: Python :: 3.10
Classifier: Programming Language :: Python :: 3.11
Requires-Python: >=3.9
Requires-Dist: numpy>=1.26.3
Requires-Dist: matplotlib>=3.8.2
Requires-Dist: pandas>=2.1.4
Requires-Dist: opencv-python>=4.9.0.80
Requires-Dist: torch>=2.1.2
Requires-Dist: torchvision>=0.16.2
Requires-Dist: scikit-image>=0.22.0
Requires-Dist: scikit-learn>=1.4.0
Requires-Dist: yacs>=0.1.8
Requires-Dist: segment-anything>=1.0
Requires-Dist: tqdm>=4.67.1
Requires-Dist: requests>=2.32.5
